{"title":"Covid-19 Cluster: 25 more tested positive","post":"2021-04-06-sunday-observer-8e74-48179607","url":"http://www.sundayobserver.lk/2021/04/04/news/covid-19-cluster-25-more-tested-positive","site":"Sunday Observer","date":"4/6/2021, 7:45:00 AM","content":"25 more persons tested positive for Covid-19, confirmed the Department of Government Information.Among them, 18 are associates of Peliyagoda Covid-19 Cluster and 07 are prisoners. The total of 122 cases reported today (04) so far.            The total number of confirmed cases rises to 88 547 from Covid-19 Clusters."}
